krxreader/__init__.py
krxreader/base.py
krxreader/calendar.py
krxreader/etf.py
krxreader/stock.py
krxreader-0.0.3.dist-info/licenses/LICENSE
krxreader-0.0.3.dist-info/METADATA
krxreader-0.0.3.dist-info/WHEEL
krxreader-0.0.3.dist-info/top_level.txt
krxreader-0.0.3.dist-info/RECORD
