Metadata-Version: 2.4
Name: krxreader
Version: 0.0.3
Summary: KRXReader is a library for scraping financial data from the KRX(Korea Exchange) Market Data System.
Author-email: Gunhoon Lee <gunhoon@gmail.com>
License: MIT License
Project-URL: Homepage, https://github.com/gunhoon/krxreader
Project-URL: Bug Tracker, https://github.com/gunhoon/krxreader/issues
Classifier: Programming Language :: Python :: 3
Classifier: License :: OSI Approved :: MIT License
Classifier: Operating System :: OS Independent
Requires-Python: >=3.9
License-File: LICENSE
Requires-Dist: krxfetch
Dynamic: license-file
